dokklib_db/__init__.py
dokklib_db/index.py
dokklib_db/keys.py
dokklib_db/op_args.py
dokklib_db/py.typed
dokklib_db/serializer.py
dokklib_db/table.py
dokklib_db/errors/__init__.py
dokklib_db/errors/client.py
dokklib_db/errors/exceptions.py
dokklib_db/errors/transaction.py
dokklib_db-0.0.15.dist-info/LICENSE
dokklib_db-0.0.15.dist-info/METADATA
dokklib_db-0.0.15.dist-info/NOTICE
dokklib_db-0.0.15.dist-info/WHEEL
dokklib_db-0.0.15.dist-info/top_level.txt
dokklib_db-0.0.15.dist-info/RECORD
