Metadata-Version: 2.1
Name: dokklib-db
Version: 0.0.15
Summary: DynamoDB Single Table Library
Home-page: https://dokklib.com/libs/db/
Author: Agost Biro
Author-email: agost+dokklib_db@dokknet.com
License: UNKNOWN
Platform: UNKNOWN
Classifier: Development Status :: 7 - Inactive
Classifier: Programming Language :: Python :: 3.8
Classifier: Programming Language :: Python :: 3.7
Classifier: Programming Language :: Python :: 3.6
Classifier: License :: OSI Approved :: Apache Software License
Classifier: Operating System :: OS Independent
Classifier: Topic :: Database
Requires-Python: >=3.6
Requires-Dist: typing-extensions (<4,>=3.7.2)
